platon_account/__init__.py
platon_account/account.py
platon_account/datastructures.py
platon_account/messages.py
platon_account/py.typed
platon_account/_utils/__init__.py
platon_account/_utils/legacy_transactions.py
platon_account/_utils/signing.py
platon_account/_utils/typed_transactions.py
platon_account/_utils/validation.py
platon_account/_utils/structured_data/__init__.py
platon_account/_utils/structured_data/hashing.py
platon_account/_utils/structured_data/validation.py
platon_account/hdaccount/__init__.py
platon_account/hdaccount/_utils.py
platon_account/hdaccount/deterministic.py
platon_account/hdaccount/mnemonic.py
platon_account/hdaccount/wordlist/chinese_simplified.txt
platon_account/hdaccount/wordlist/chinese_traditional.txt
platon_account/hdaccount/wordlist/czech.txt
platon_account/hdaccount/wordlist/english.txt
platon_account/hdaccount/wordlist/french.txt
platon_account/hdaccount/wordlist/italian.txt
platon_account/hdaccount/wordlist/japanese.txt
platon_account/hdaccount/wordlist/korean.txt
platon_account/hdaccount/wordlist/spanish.txt
platon_account/signers/__init__.py
platon_account/signers/base.py
platon_account/signers/local.py
platon_account-1.2.1.dist-info/LICENSE
platon_account-1.2.1.dist-info/METADATA
platon_account-1.2.1.dist-info/WHEEL
platon_account-1.2.1.dist-info/top_level.txt
platon_account-1.2.1.dist-info/RECORD
