Metadata-Version: 2.1
Name: platon-account
Version: 1.2.1
Summary: platon-account: Sign Platon transactions and messages with local private keys
Home-page: https://github.com/platonnetwork/platon-account
Author: Shinnng
Author-email: Shinnng@outlook.com
License: MIT
Keywords: platon
Platform: UNKNOWN
Classifier: Development Status :: 3 - Alpha
Classifier: Intended Audience :: Developers
Classifier: License :: OSI Approved :: MIT License
Classifier: Natural Language :: English
Classifier: Operating System :: MacOS
Classifier: Operating System :: POSIX
Classifier: Programming Language :: Python :: 3
Classifier: Programming Language :: Python :: 3.6
Classifier: Programming Language :: Python :: 3.7
Classifier: Programming Language :: Python :: 3.8
Requires-Python: >=3.6, <4
License-File: LICENSE
Requires-Dist: bitarray (<1.3.0,>=1.2.1)
Requires-Dist: platon-abi (>=1.2.0)
Requires-Dist: platon-keyfile (>=1.2.0)
Requires-Dist: platon-keys (>=1.2.0)
Requires-Dist: platon-rlp (>=1.2.0)
Requires-Dist: platon-utils (>=1.2.0)
Requires-Dist: hexbytes (<1,>=0.1.0)
Requires-Dist: rlp (<3,>=1.0.0)
Provides-Extra: dev
Requires-Dist: bumpversion (<1,>=0.5.3) ; extra == 'dev'
Requires-Dist: pytest-watch (<5,>=4.1.0) ; extra == 'dev'
Requires-Dist: wheel ; extra == 'dev'
Requires-Dist: twine ; extra == 'dev'
Requires-Dist: ipython ; extra == 'dev'
Requires-Dist: hypothesis (<5,>=4.18.0) ; extra == 'dev'
Requires-Dist: pytest (==5.4.1) ; extra == 'dev'
Requires-Dist: pytest-xdist ; extra == 'dev'
Requires-Dist: tox (==3.14.6) ; extra == 'dev'
Requires-Dist: flake8 (==3.7.9) ; extra == 'dev'
Requires-Dist: isort (<5,>=4.2.15) ; extra == 'dev'
Requires-Dist: mypy (==0.770) ; extra == 'dev'
Requires-Dist: pydocstyle (<6,>=5.0.0) ; extra == 'dev'
Requires-Dist: Sphinx (<2,>=1.6.5) ; extra == 'dev'
Requires-Dist: sphinx-rtd-theme (<1,>=0.1.9) ; extra == 'dev'
Requires-Dist: towncrier (<20,>=19.2.0) ; extra == 'dev'
Provides-Extra: doc
Requires-Dist: Sphinx (<2,>=1.6.5) ; extra == 'doc'
Requires-Dist: sphinx-rtd-theme (<1,>=0.1.9) ; extra == 'doc'
Requires-Dist: towncrier (<20,>=19.2.0) ; extra == 'doc'
Provides-Extra: lint
Requires-Dist: flake8 (==3.7.9) ; extra == 'lint'
Requires-Dist: isort (<5,>=4.2.15) ; extra == 'lint'
Requires-Dist: mypy (==0.770) ; extra == 'lint'
Requires-Dist: pydocstyle (<6,>=5.0.0) ; extra == 'lint'
Provides-Extra: test
Requires-Dist: hypothesis (<5,>=4.18.0) ; extra == 'test'
Requires-Dist: pytest (==5.4.1) ; extra == 'test'
Requires-Dist: pytest-xdist ; extra == 'test'
Requires-Dist: tox (==3.14.6) ; extra == 'test'
